data_generator_postgresql/__init__.py
data_generator_postgresql/data_generator.py
data_generator_postgresql/insert_to_db.py
data_generator_postgresql_pkg-0.0.1.3.dist-info/LICENSE
data_generator_postgresql_pkg-0.0.1.3.dist-info/METADATA
data_generator_postgresql_pkg-0.0.1.3.dist-info/WHEEL
data_generator_postgresql_pkg-0.0.1.3.dist-info/top_level.txt
data_generator_postgresql_pkg-0.0.1.3.dist-info/RECORD
