Metadata-Version: 2.1
Name: data-generator-postgresql-pkg
Version: 0.0.1.3
Summary: Data generator for postgres
Home-page: https://example.com
Author: Tarasenko Stepan
Author-email: st.a.tarasenko@gmail.com
License: UNKNOWN
Platform: UNKNOWN
Classifier: Programming Language :: Python :: 3
Classifier: License :: OSI Approved :: MIT License
Classifier: Operating System :: OS Independent
